{
  "slug": "seoul/geumcheon",
  "name": "금천구",
  "name_full": "서울특별시 금천구",
  "level": "gu",
  "lawd_cd": "11545",
  "fetched_at": "2026-05-03T01:51:51.946929+00:00",
  "sections": {
    "real_estate_trade": {
      "count": 213,
      "median_price_per_pyeong_man": 2797,
      "mean_price_per_pyeong_man": 3051,
      "median_deal_amount_man": 58300,
      "period_months": [
        "202604",
        "202603"
      ],
      "monthly_count_avg": 106.5
    },
    "real_estate_rent": {
      "total_count": 415,
      "jeonse_count": 202,
      "monthly_count": 213,
      "median_jeonse_man": 38000,
      "mean_jeonse_man": 37949,
      "period_months": [
        "202604",
        "202603"
      ]
    },
    "environment": {
      "seoul_avg": {
        "pm10": 18,
        "pm25": 12,
        "station_count": 40
      },
      "gangnam_station": {
        "station": "금천구",
        "pm10": null,
        "pm25": 25
      },
      "gu_station": {
        "station": "금천구",
        "pm10": null,
        "pm25": 25
      },
      "measured_at": "2026-05-03 10:00"
    },
    "medical": {
      "sgg_count": 174,
      "by_type": {
        "종합병원": 1,
        "병원": 5,
        "요양병원": 3,
        "정신병원": 1,
        "의원": 164
      }
    },
    "education": {
      "sgg_count": 35,
      "by_type": {
        "중학교": 9,
        "고등학교": 6,
        "각종학교(중)": 1,
        "각종학교(고)": 1,
        "초등학교": 18
      }
    },
    "population": {
      "table_id": "DT_1B040A3",
      "table_name": "행정구역(시군구)별/성별 인구수",
      "period": "202603",
      "sgg_total": 222712,
      "gangnam_total": 222712,
      "seoul_total": 9304400,
      "share_of_seoul_pct": 2.39
    }
  },
  "errors": []
}